{
    "type": "root",
    "children": [
        {
            "type": "element",
            "tagName": "p",
            "properties": {},
            "children": [
                {
                    "type": "text",
                    "value": "By changing the ",
                    "position": {
                        "start": {
                            "line": 1,
                            "column": 1,
                            "offset": 0
                        },
                        "end": {
                            "line": 1,
                            "column": 17,
                            "offset": 16
                        }
                    }
                },
                {
                    "type": "element",
                    "tagName": "code",
                    "properties": {},
                    "children": [
                        {
                            "type": "text",
                            "value": "Class.IKControl.Type|Type"
                        }
                    ],
                    "position": {
                        "start": {
                            "line": 1,
                            "column": 17,
                            "offset": 16
                        },
                        "end": {
                            "line": 1,
                            "column": 44,
                            "offset": 43
                        }
                    }
                },
                {
                    "type": "text",
                    "value": ", you can change the behavior\nof the control. These are the available options:",
                    "position": {
                        "start": {
                            "line": 1,
                            "column": 44,
                            "offset": 43
                        },
                        "end": {
                            "line": 2,
                            "column": 49,
                            "offset": 121
                        }
                    }
                }
            ],
            "position": {
                "start": {
                    "line": 1,
                    "column": 1,
                    "offset": 0
                },
                "end": {
                    "line": 2,
                    "column": 49,
                    "offset": 121
                }
            }
        },
        {
            "type": "text",
            "value": "\n"
        },
        {
            "type": "element",
            "tagName": "ul",
            "properties": {},
            "children": [
                {
                    "type": "text",
                    "value": "\n"
                },
                {
                    "type": "element",
                    "tagName": "li",
                    "properties": {},
                    "children": [
                        {
                            "type": "text",
                            "value": "Transform: it's a full 6-DoF constraint. Aligns the\n",
                            "position": {
                                "start": {
                                    "line": 4,
                                    "column": 3,
                                    "offset": 125
                                },
                                "end": {
                                    "line": 5,
                                    "column": 1,
                                    "offset": 177
                                }
                            }
                        },
                        {
                            "type": "element",
                            "tagName": "code",
                            "properties": {},
                            "children": [
                                {
                                    "type": "text",
                                    "value": "Class.IKControl.EndEffector|EndEffector"
                                }
                            ],
                            "position": {
                                "start": {
                                    "line": 5,
                                    "column": 3,
                                    "offset": 179
                                },
                                "end": {
                                    "line": 5,
                                    "column": 44,
                                    "offset": 220
                                }
                            }
                        },
                        {
                            "type": "text",
                            "value": " ",
                            "position": {
                                "start": {
                                    "line": 5,
                                    "column": 44,
                                    "offset": 220
                                },
                                "end": {
                                    "line": 5,
                                    "column": 45,
                                    "offset": 221
                                }
                            }
                        },
                        {
                            "type": "element",
                            "tagName": "code",
                            "properties": {},
                            "children": [
                                {
                                    "type": "text",
                                    "value": "Datatype.CFrame"
                                }
                            ],
                            "position": {
                                "start": {
                                    "line": 5,
                                    "column": 45,
                                    "offset": 221
                                },
                                "end": {
                                    "line": 5,
                                    "column": 62,
                                    "offset": 238
                                }
                            }
                        },
                        {
                            "type": "text",
                            "value": " to that of\nthe ",
                            "position": {
                                "start": {
                                    "line": 5,
                                    "column": 62,
                                    "offset": 238
                                },
                                "end": {
                                    "line": 6,
                                    "column": 7,
                                    "offset": 256
                                }
                            }
                        },
                        {
                            "type": "element",
                            "tagName": "code",
                            "properties": {},
                            "children": [
                                {
                                    "type": "text",
                                    "value": "Class.IKControl.Target|Target"
                                }
                            ],
                            "position": {
                                "start": {
                                    "line": 6,
                                    "column": 7,
                                    "offset": 256
                                },
                                "end": {
                                    "line": 6,
                                    "column": 38,
                                    "offset": 287
                                }
                            }
                        },
                        {
                            "type": "text",
                            "value": ".",
                            "position": {
                                "start": {
                                    "line": 6,
                                    "column": 38,
                                    "offset": 287
                                },
                                "end": {
                                    "line": 6,
                                    "column": 39,
                                    "offset": 288
                                }
                            }
                        }
                    ],
                    "position": {
                        "start": {
                            "line": 4,
                            "column": 1,
                            "offset": 123
                        },
                        "end": {
                            "line": 6,
                            "column": 39,
                            "offset": 288
                        }
                    }
                },
                {
                    "type": "text",
                    "value": "\n"
                },
                {
                    "type": "element",
                    "tagName": "li",
                    "properties": {},
                    "children": [
                        {
                            "type": "text",
                            "value": "Position: aligns the ",
                            "position": {
                                "start": {
                                    "line": 7,
                                    "column": 3,
                                    "offset": 291
                                },
                                "end": {
                                    "line": 7,
                                    "column": 24,
                                    "offset": 312
                                }
                            }
                        },
                        {
                            "type": "element",
                            "tagName": "code",
                            "properties": {},
                            "children": [
                                {
                                    "type": "text",
                                    "value": "Class.IKControl.EndEffector|EndEffector"
                                }
                            ],
                            "position": {
                                "start": {
                                    "line": 7,
                                    "column": 24,
                                    "offset": 312
                                },
                                "end": {
                                    "line": 7,
                                    "column": 65,
                                    "offset": 353
                                }
                            }
                        },
                        {
                            "type": "text",
                            "value": " position\nto that of the ",
                            "position": {
                                "start": {
                                    "line": 7,
                                    "column": 65,
                                    "offset": 353
                                },
                                "end": {
                                    "line": 8,
                                    "column": 18,
                                    "offset": 380
                                }
                            }
                        },
                        {
                            "type": "element",
                            "tagName": "code",
                            "properties": {},
                            "children": [
                                {
                                    "type": "text",
                                    "value": "Class.IKControl.Target|Target"
                                }
                            ],
                            "position": {
                                "start": {
                                    "line": 8,
                                    "column": 18,
                                    "offset": 380
                                },
                                "end": {
                                    "line": 8,
                                    "column": 49,
                                    "offset": 411
                                }
                            }
                        },
                        {
                            "type": "text",
                            "value": ".",
                            "position": {
                                "start": {
                                    "line": 8,
                                    "column": 49,
                                    "offset": 411
                                },
                                "end": {
                                    "line": 8,
                                    "column": 50,
                                    "offset": 412
                                }
                            }
                        }
                    ],
                    "position": {
                        "start": {
                            "line": 7,
                            "column": 1,
                            "offset": 289
                        },
                        "end": {
                            "line": 8,
                            "column": 50,
                            "offset": 412
                        }
                    }
                },
                {
                    "type": "text",
                    "value": "\n"
                },
                {
                    "type": "element",
                    "tagName": "li",
                    "properties": {},
                    "children": [
                        {
                            "type": "text",
                            "value": "Rotation: aligns the ",
                            "position": {
                                "start": {
                                    "line": 9,
                                    "column": 3,
                                    "offset": 415
                                },
                                "end": {
                                    "line": 9,
                                    "column": 24,
                                    "offset": 436
                                }
                            }
                        },
                        {
                            "type": "element",
                            "tagName": "code",
                            "properties": {},
                            "children": [
                                {
                                    "type": "text",
                                    "value": "Class.IKControl.EndEffector|EndEffector"
                                }
                            ],
                            "position": {
                                "start": {
                                    "line": 9,
                                    "column": 24,
                                    "offset": 436
                                },
                                "end": {
                                    "line": 9,
                                    "column": 65,
                                    "offset": 477
                                }
                            }
                        },
                        {
                            "type": "text",
                            "value": " rotation\nto that of the ",
                            "position": {
                                "start": {
                                    "line": 9,
                                    "column": 65,
                                    "offset": 477
                                },
                                "end": {
                                    "line": 10,
                                    "column": 18,
                                    "offset": 504
                                }
                            }
                        },
                        {
                            "type": "element",
                            "tagName": "code",
                            "properties": {},
                            "children": [
                                {
                                    "type": "text",
                                    "value": "Class.IKControl.Target|Target"
                                }
                            ],
                            "position": {
                                "start": {
                                    "line": 10,
                                    "column": 18,
                                    "offset": 504
                                },
                                "end": {
                                    "line": 10,
                                    "column": 49,
                                    "offset": 535
                                }
                            }
                        },
                        {
                            "type": "text",
                            "value": ".",
                            "position": {
                                "start": {
                                    "line": 10,
                                    "column": 49,
                                    "offset": 535
                                },
                                "end": {
                                    "line": 10,
                                    "column": 50,
                                    "offset": 536
                                }
                            }
                        }
                    ],
                    "position": {
                        "start": {
                            "line": 9,
                            "column": 1,
                            "offset": 413
                        },
                        "end": {
                            "line": 10,
                            "column": 50,
                            "offset": 536
                        }
                    }
                },
                {
                    "type": "text",
                    "value": "\n"
                },
                {
                    "type": "element",
                    "tagName": "li",
                    "properties": {},
                    "children": [
                        {
                            "type": "text",
                            "value": "LookAt: moves and orients the whole chain to make an axis (by default\nthe forward axis) on the ",
                            "position": {
                                "start": {
                                    "line": 11,
                                    "column": 3,
                                    "offset": 539
                                },
                                "end": {
                                    "line": 12,
                                    "column": 28,
                                    "offset": 636
                                }
                            }
                        },
                        {
                            "type": "element",
                            "tagName": "code",
                            "properties": {},
                            "children": [
                                {
                                    "type": "text",
                                    "value": "Class.IKControl.EndEffector|EndEffector"
                                }
                            ],
                            "position": {
                                "start": {
                                    "line": 12,
                                    "column": 28,
                                    "offset": 636
                                },
                                "end": {
                                    "line": 12,
                                    "column": 69,
                                    "offset": 677
                                }
                            }
                        },
                        {
                            "type": "text",
                            "value": " point\nat a position in the world specified by ",
                            "position": {
                                "start": {
                                    "line": 12,
                                    "column": 69,
                                    "offset": 677
                                },
                                "end": {
                                    "line": 13,
                                    "column": 43,
                                    "offset": 726
                                }
                            }
                        },
                        {
                            "type": "element",
                            "tagName": "code",
                            "properties": {},
                            "children": [
                                {
                                    "type": "text",
                                    "value": "Class.IKControl.Target|Target"
                                }
                            ],
                            "position": {
                                "start": {
                                    "line": 13,
                                    "column": 43,
                                    "offset": 726
                                },
                                "end": {
                                    "line": 13,
                                    "column": 74,
                                    "offset": 757
                                }
                            }
                        },
                        {
                            "type": "text",
                            "value": ".",
                            "position": {
                                "start": {
                                    "line": 13,
                                    "column": 74,
                                    "offset": 757
                                },
                                "end": {
                                    "line": 13,
                                    "column": 75,
                                    "offset": 758
                                }
                            }
                        }
                    ],
                    "position": {
                        "start": {
                            "line": 11,
                            "column": 1,
                            "offset": 537
                        },
                        "end": {
                            "line": 13,
                            "column": 75,
                            "offset": 758
                        }
                    }
                },
                {
                    "type": "text",
                    "value": "\n"
                }
            ],
            "position": {
                "start": {
                    "line": 4,
                    "column": 1,
                    "offset": 123
                },
                "end": {
                    "line": 13,
                    "column": 75,
                    "offset": 758
                }
            }
        }
    ],
    "data": {
        "quirksMode": false
    },
    "position": {
        "start": {
            "line": 1,
            "column": 1,
            "offset": 0
        },
        "end": {
            "line": 1,
            "column": 1,
            "offset": 0
        }
    }
}