{
    "type": "root",
    "children": [
        {
            "type": "element",
            "tagName": "p",
            "properties": {},
            "children": [
                {
                    "type": "text",
                    "value": "A ",
                    "position": {
                        "start": {
                            "line": 1,
                            "column": 1,
                            "offset": 0
                        },
                        "end": {
                            "line": 1,
                            "column": 3,
                            "offset": 2
                        }
                    }
                },
                {
                    "type": "element",
                    "tagName": "strong",
                    "properties": {},
                    "children": [
                        {
                            "type": "text",
                            "value": "PrismaticConstraint",
                            "position": {
                                "start": {
                                    "line": 1,
                                    "column": 5,
                                    "offset": 4
                                },
                                "end": {
                                    "line": 1,
                                    "column": 24,
                                    "offset": 23
                                }
                            }
                        }
                    ],
                    "position": {
                        "start": {
                            "line": 1,
                            "column": 3,
                            "offset": 2
                        },
                        "end": {
                            "line": 1,
                            "column": 26,
                            "offset": 25
                        }
                    }
                },
                {
                    "type": "text",
                    "value": " creates a rigid joint between two\n",
                    "position": {
                        "start": {
                            "line": 1,
                            "column": 26,
                            "offset": 25
                        },
                        "end": {
                            "line": 2,
                            "column": 1,
                            "offset": 60
                        }
                    }
                },
                {
                    "type": "element",
                    "tagName": "code",
                    "properties": {},
                    "children": [
                        {
                            "type": "text",
                            "value": "Class.Attachment|Attachments"
                        }
                    ],
                    "position": {
                        "start": {
                            "line": 2,
                            "column": 1,
                            "offset": 60
                        },
                        "end": {
                            "line": 2,
                            "column": 31,
                            "offset": 90
                        }
                    }
                },
                {
                    "type": "text",
                    "value": ", allowing them to slide along one axis but not\nrotate. This constrains the attachments so that their ",
                    "position": {
                        "start": {
                            "line": 2,
                            "column": 31,
                            "offset": 90
                        },
                        "end": {
                            "line": 3,
                            "column": 55,
                            "offset": 192
                        }
                    }
                },
                {
                    "type": "element",
                    "tagName": "strong",
                    "properties": {},
                    "children": [
                        {
                            "type": "text",
                            "value": "X",
                            "position": {
                                "start": {
                                    "line": 3,
                                    "column": 57,
                                    "offset": 194
                                },
                                "end": {
                                    "line": 3,
                                    "column": 58,
                                    "offset": 195
                                }
                            }
                        }
                    ],
                    "position": {
                        "start": {
                            "line": 3,
                            "column": 55,
                            "offset": 192
                        },
                        "end": {
                            "line": 3,
                            "column": 60,
                            "offset": 197
                        }
                    }
                },
                {
                    "type": "text",
                    "value": " axes are collinear\nbut pointing in opposite directions. It also constrains the attachments so\nthat their ",
                    "position": {
                        "start": {
                            "line": 3,
                            "column": 60,
                            "offset": 197
                        },
                        "end": {
                            "line": 5,
                            "column": 12,
                            "offset": 303
                        }
                    }
                },
                {
                    "type": "element",
                    "tagName": "strong",
                    "properties": {},
                    "children": [
                        {
                            "type": "text",
                            "value": "Y",
                            "position": {
                                "start": {
                                    "line": 5,
                                    "column": 14,
                                    "offset": 305
                                },
                                "end": {
                                    "line": 5,
                                    "column": 15,
                                    "offset": 306
                                }
                            }
                        }
                    ],
                    "position": {
                        "start": {
                            "line": 5,
                            "column": 12,
                            "offset": 303
                        },
                        "end": {
                            "line": 5,
                            "column": 17,
                            "offset": 308
                        }
                    }
                },
                {
                    "type": "text",
                    "value": " axes are parallel.",
                    "position": {
                        "start": {
                            "line": 5,
                            "column": 17,
                            "offset": 308
                        },
                        "end": {
                            "line": 5,
                            "column": 36,
                            "offset": 327
                        }
                    }
                }
            ],
            "position": {
                "start": {
                    "line": 1,
                    "column": 1,
                    "offset": 0
                },
                "end": {
                    "line": 5,
                    "column": 36,
                    "offset": 327
                }
            }
        },
        {
            "type": "text",
            "value": "\n"
        },
        {
            "type": "element",
            "tagName": "p",
            "properties": {},
            "children": [
                {
                    "type": "text",
                    "value": "This constraint inherits many properties from ",
                    "position": {
                        "start": {
                            "line": 7,
                            "column": 1,
                            "offset": 329
                        },
                        "end": {
                            "line": 7,
                            "column": 47,
                            "offset": 375
                        }
                    }
                },
                {
                    "type": "element",
                    "tagName": "code",
                    "properties": {},
                    "children": [
                        {
                            "type": "text",
                            "value": "Class.SlidingBallConstraint"
                        }
                    ],
                    "position": {
                        "start": {
                            "line": 7,
                            "column": 47,
                            "offset": 375
                        },
                        "end": {
                            "line": 7,
                            "column": 76,
                            "offset": 404
                        }
                    }
                },
                {
                    "type": "text",
                    "value": "\nincluding ",
                    "position": {
                        "start": {
                            "line": 7,
                            "column": 76,
                            "offset": 404
                        },
                        "end": {
                            "line": 8,
                            "column": 11,
                            "offset": 415
                        }
                    }
                },
                {
                    "type": "element",
                    "tagName": "code",
                    "properties": {},
                    "children": [
                        {
                            "type": "text",
                            "value": "Class.SlidingBallConstraint.ActuatorType|ActuatorType"
                        }
                    ],
                    "position": {
                        "start": {
                            "line": 8,
                            "column": 11,
                            "offset": 415
                        },
                        "end": {
                            "line": 8,
                            "column": 66,
                            "offset": 470
                        }
                    }
                },
                {
                    "type": "text",
                    "value": ",\n",
                    "position": {
                        "start": {
                            "line": 8,
                            "column": 66,
                            "offset": 470
                        },
                        "end": {
                            "line": 9,
                            "column": 1,
                            "offset": 472
                        }
                    }
                },
                {
                    "type": "element",
                    "tagName": "code",
                    "properties": {},
                    "children": [
                        {
                            "type": "text",
                            "value": "Class.SlidingBallConstraint.LimitsEnabled|LimitsEnabled"
                        }
                    ],
                    "position": {
                        "start": {
                            "line": 9,
                            "column": 1,
                            "offset": 472
                        },
                        "end": {
                            "line": 9,
                            "column": 58,
                            "offset": 529
                        }
                    }
                },
                {
                    "type": "text",
                    "value": ",\n",
                    "position": {
                        "start": {
                            "line": 9,
                            "column": 58,
                            "offset": 529
                        },
                        "end": {
                            "line": 10,
                            "column": 1,
                            "offset": 531
                        }
                    }
                },
                {
                    "type": "element",
                    "tagName": "code",
                    "properties": {},
                    "children": [
                        {
                            "type": "text",
                            "value": "Class.SlidingBallConstraint.Velocity|Velocity"
                        }
                    ],
                    "position": {
                        "start": {
                            "line": 10,
                            "column": 1,
                            "offset": 531
                        },
                        "end": {
                            "line": 10,
                            "column": 48,
                            "offset": 578
                        }
                    }
                },
                {
                    "type": "text",
                    "value": ", and more. Please refer to\n",
                    "position": {
                        "start": {
                            "line": 10,
                            "column": 48,
                            "offset": 578
                        },
                        "end": {
                            "line": 11,
                            "column": 1,
                            "offset": 606
                        }
                    }
                },
                {
                    "type": "element",
                    "tagName": "code",
                    "properties": {},
                    "children": [
                        {
                            "type": "text",
                            "value": "Class.SlidingBallConstraint"
                        }
                    ],
                    "position": {
                        "start": {
                            "line": 11,
                            "column": 1,
                            "offset": 606
                        },
                        "end": {
                            "line": 11,
                            "column": 30,
                            "offset": 635
                        }
                    }
                },
                {
                    "type": "text",
                    "value": " for details on configuring a\n",
                    "position": {
                        "start": {
                            "line": 11,
                            "column": 30,
                            "offset": 635
                        },
                        "end": {
                            "line": 12,
                            "column": 1,
                            "offset": 665
                        }
                    }
                },
                {
                    "type": "element",
                    "tagName": "code",
                    "properties": {},
                    "children": [
                        {
                            "type": "text",
                            "value": "Class.PrismaticConstraint"
                        }
                    ],
                    "position": {
                        "start": {
                            "line": 12,
                            "column": 1,
                            "offset": 665
                        },
                        "end": {
                            "line": 12,
                            "column": 28,
                            "offset": 692
                        }
                    }
                },
                {
                    "type": "text",
                    "value": ".",
                    "position": {
                        "start": {
                            "line": 12,
                            "column": 28,
                            "offset": 692
                        },
                        "end": {
                            "line": 12,
                            "column": 29,
                            "offset": 693
                        }
                    }
                }
            ],
            "position": {
                "start": {
                    "line": 7,
                    "column": 1,
                    "offset": 329
                },
                "end": {
                    "line": 12,
                    "column": 29,
                    "offset": 693
                }
            }
        },
        {
            "type": "text",
            "value": "\n"
        },
        {
            "type": "element",
            "tagName": "p",
            "properties": {},
            "children": [
                {
                    "type": "text",
                    "value": "When configuring this constraint, it may be helpful to study\n",
                    "position": {
                        "start": {
                            "line": 14,
                            "column": 1,
                            "offset": 695
                        },
                        "end": {
                            "line": 15,
                            "column": 1,
                            "offset": 756
                        }
                    }
                },
                {
                    "type": "element",
                    "tagName": "a",
                    "properties": {
                        "href": "/physics/units"
                    },
                    "children": [
                        {
                            "type": "text",
                            "value": "Roblox Units",
                            "position": {
                                "start": {
                                    "line": 15,
                                    "column": 2,
                                    "offset": 757
                                },
                                "end": {
                                    "line": 15,
                                    "column": 14,
                                    "offset": 769
                                }
                            }
                        }
                    ],
                    "position": {
                        "start": {
                            "line": 15,
                            "column": 1,
                            "offset": 756
                        },
                        "end": {
                            "line": 15,
                            "column": 31,
                            "offset": 786
                        }
                    }
                },
                {
                    "type": "text",
                    "value": " to understand how Roblox units\ncompare to metric units.",
                    "position": {
                        "start": {
                            "line": 15,
                            "column": 31,
                            "offset": 786
                        },
                        "end": {
                            "line": 16,
                            "column": 25,
                            "offset": 842
                        }
                    }
                }
            ],
            "position": {
                "start": {
                    "line": 14,
                    "column": 1,
                    "offset": 695
                },
                "end": {
                    "line": 16,
                    "column": 25,
                    "offset": 842
                }
            }
        }
    ],
    "data": {
        "quirksMode": false
    },
    "position": {
        "start": {
            "line": 1,
            "column": 1,
            "offset": 0
        },
        "end": {
            "line": 1,
            "column": 1,
            "offset": 0
        }
    }
}